decorators/__init__.py
decorators/timeout/__init__.py
decorators/timeout/timeout_decorator.py
loggers/__init__.py
loggers/default/__init__.py
loggers/default/logger.py
utils/__init__.py
utils/datetime/__init__.py
utils/datetime/datetime_utils.py
utils/email/__init__.py
utils/email/email_utils.py
utils/encode/__init__.py
utils/encode/automatic_switch_python_version.py
utils/encode/encode_utils.py
utils/image/__init__.py
utils/image/image_utils.py
utils/redis/__init__.py
utils/redis/redis_key_util.py
utils/redis/redis_utils.py
utils/wechat_work/__init__.py
utils/wechat_work/robot_message_builder_util.py
utils/wechat_work/robot_message_sender_util.py
qrcericcommons-0.1.0.dist-info/LICENSE
qrcericcommons-0.1.0.dist-info/METADATA
qrcericcommons-0.1.0.dist-info/WHEEL
qrcericcommons-0.1.0.dist-info/entry_points.txt
qrcericcommons-0.1.0.dist-info/top_level.txt
qrcericcommons-0.1.0.dist-info/RECORD
