Metadata-Version: 2.1
Name: qrcericcommons
Version: 0.1.0
Summary: Common utils for python.
Home-page: https://github.com/QrCer/qrcer_commons
Author: DongQirui
Author-email: QrCeric@Gmail.com
License: UNKNOWN
Keywords: common utils python base
Platform: UNKNOWN
Classifier: Programming Language :: Python :: 3
Classifier: License :: OSI Approved :: MIT License
Classifier: Operating System :: OS Independent
Requires-Dist: redis
